arduinoSNT/__init__.py
arduinoSNT/arduinoSNT.py
arduinoSNT/board.py
arduinoSNT/button.py
arduinoSNT/exceptions.py
arduinoSNT/led.py
arduino_snt-1.1.3.dist-info/METADATA
arduino_snt-1.1.3.dist-info/WHEEL
arduino_snt-1.1.3.dist-info/top_level.txt
arduino_snt-1.1.3.dist-info/RECORD
