Metadata-Version: 2.2
Name: arduino-snt
Version: 1.1.3
Summary: Python package to easily control an arduino using Python.
Home-page: https://github.com/Amzu-bzh/arduino-snt
Author: Amaury GODOT
Classifier: Development Status :: 2 - Pre-Alpha
Classifier: Programming Language :: Python
Classifier: Programming Language :: Python :: 3
Classifier: Programming Language :: Python :: 3.12
Requires-Dist: pyfirmata>=1.1.0
Dynamic: author
Dynamic: classifier
Dynamic: description
Dynamic: description-content-type
Dynamic: home-page
Dynamic: requires-dist
Dynamic: summary
